cell_flower/__init__.py
cell_flower/cell_complex.py
cell_flower/detection.py
cell_flower/matrix_utils.py
cell_flower/spanning_trees.py
cell_flower-1.0.1.dist-info/METADATA
cell_flower-1.0.1.dist-info/WHEEL
cell_flower-1.0.1.dist-info/licenses/LICENSE
cell_flower-1.0.1.dist-info/RECORD
