Metadata-Version: 2.3
Name: cell-flower
Version: 1.0.1
Summary: Cell FLOWer processes edge flows using cell complexes.
Project-URL: Homepage, https://github.com/josefhoppe/cell-flower
Project-URL: Bug Tracker, https://github.com/josefhoppe/cell-flower/issues
Author-email: Josef Hoppe <hoppe@cs.rwth-aachen.de>
License-File: LICENSE
Classifier: License :: OSI Approved :: MIT License
Classifier: Operating System :: OS Independent
Classifier: Programming Language :: Python :: 3
Requires-Python: >=3.10
Requires-Dist: numpy>=1.20.0
Requires-Dist: scikit-learn>=1.2.0
Requires-Dist: scipy>=1.10.0
Provides-Extra: test
Requires-Dist: networkx; extra == 'test'
Requires-Dist: pandas; extra == 'test'
Requires-Dist: pytest-cov; extra == 'test'
